LICENSE
MANIFEST.in
README.md
VERSION
pyproject.toml
setup.cfg
setup.py
zeek-client
tests/test_brokertypes.py
tests/test_cli.py
tests/test_config_io.py
tests/test_config_overrides.py
tests/test_controller.py
tests/test_types.py
zeek_client.egg-info/PKG-INFO
zeek_client.egg-info/SOURCES.txt
zeek_client.egg-info/dependency_links.txt
zeek_client.egg-info/requires.txt
zeek_client.egg-info/top_level.txt
zeekclient/__init__.py
zeekclient/brokertypes.py
zeekclient/cli.py
zeekclient/config.py
zeekclient/consts.py
zeekclient/controller.py
zeekclient/events.py
zeekclient/logs.py
zeekclient/ssl.py
zeekclient/types.py
zeekclient/utils.py