Metadata-Version: 2.4
Name: zeek-client
Version: 1.5.0
Summary: A CLI for Zeek's Management Framework
Maintainer-email: The Zeek Project <info@zeek.org>
License: 3-clause BSD License
Project-URL: Repository, https://github.com/zeek/zeek-client
Keywords: zeek,management,client,cluster
Classifier: Development Status :: 4 - Beta
Classifier: Environment :: Console
Classifier: License :: OSI Approved :: BSD License
Classifier: Operating System :: POSIX :: Linux
Classifier: Operating System :: MacOS :: MacOS X
Classifier: Programming Language :: Python :: 3
Classifier: Topic :: System :: Networking :: Monitoring
Classifier: Topic :: Utilities
Requires-Python: >=3.9
License-File: LICENSE
Requires-Dist: websocket-client>=1.8.0
Requires-Dist: argcomplete>=3.4.0
Requires-Dist: argparse>=1.4.0
Provides-Extra: dev
Requires-Dist: pytest>=8.1.1; extra == "dev"
Requires-Dist: pytest-cov>=5.0.0; extra == "dev"
Dynamic: license-file
